johnnycanencrypt-0.18.0.dist-info/METADATA
johnnycanencrypt-0.18.0.dist-info/WHEEL
johnnycanencrypt-0.18.0.dist-info/licenses/LICENSE
johnnycanencrypt/__init__.py
johnnycanencrypt/exceptions.py
johnnycanencrypt/johnnycanencrypt.cpython-314t-darwin.so
johnnycanencrypt/johnnycanencrypt.pyi
johnnycanencrypt/py.typed
johnnycanencrypt/utils.py
johnnycanencrypt-0.18.0.dist-info/RECORD
