Metadata-Version: 2.4
Name: johnnycanencrypt
Version: 0.18.0
Classifier: Development Status :: 4 - Beta
Classifier: License :: OSI Approved :: GNU Lesser General Public License v3 or later (LGPLv3+)
Classifier: Programming Language :: Rust
Classifier: Programming Language :: Python
Classifier: Programming Language :: Python :: 3 :: Only
Classifier: Programming Language :: Python :: 3.8
Classifier: Programming Language :: Python :: 3.9
Classifier: Programming Language :: Python :: 3.10
Classifier: Programming Language :: Python :: 3.11
Classifier: Programming Language :: Python :: Implementation :: CPython
Classifier: Topic :: Software Development :: Libraries
Classifier: Topic :: Software Development :: Libraries :: Python Modules
Requires-Dist: httpx
Requires-Dist: tzdata
License-File: LICENSE
Home-Page: https://johnnycanencrypt.readthedocs.io/en/latest/introduction.html
Author-email: Kushal Das <mail@kushaldas.in>
Requires-Python: >=3.8
Project-URL: Homepage, https://github.com/kushaldas/johnnycanencrypt
Project-URL: Bug Tracker, https://github.com/kushaldas/johnnycanencrypt/issues
